sl_whatsapp/__init__.py
sl_whatsapp/__main__.py
sl_whatsapp-1.3.9.dist-info/LICENSE
sl_whatsapp-1.3.9.dist-info/METADATA
sl_whatsapp-1.3.9.dist-info/WHEEL
sl_whatsapp-1.3.9.dist-info/entry_points.txt
sl_whatsapp-1.3.9.dist-info/top_level.txt
sl_whatsapp-1.3.9.dist-info/RECORD
